<?xml version="1.0" encoding="utf-8"?>
<cms.webpageitem>
  <WebPageItemContentItemID>
    <CodeName>SubHome-z8s0yx57</CodeName>
    <GUID>b13c670f-a600-48a5-b422-571299175d9b</GUID>
    <ObjectType>cms.contentitem</ObjectType>
  </WebPageItemContentItemID>
  <WebPageItemGUID>dcfb4b5b-4471-4ee7-962a-acab89463aa4</WebPageItemGUID>
  <WebPageItemName>SubHome-z8s0yx57</WebPageItemName>
  <WebPageItemOrder>1</WebPageItemOrder>
  <WebPageItemParentID>
    <CodeName>Home-kwlgvu2o</CodeName>
    <GUID>7912bf1c-326b-4efe-bdad-7ba7635ce69b</GUID>
    <ObjectType>cms.webpageitem</ObjectType>
  </WebPageItemParentID>
  <WebPageItemTreePath>/Home/SubHome</WebPageItemTreePath>
  <WebPageItemWebsiteChannelID>
    <GUID>8f77535e-1d86-4278-bb96-d2c0844b7cf0</GUID>
    <ObjectType>cms.websitechannel</ObjectType>
    <Parent>
      <CodeName>Photosnap</CodeName>
      <GUID>ca1743fb-f454-4369-afbe-844f2af4aed0</GUID>
      <ObjectType>cms.channel</ObjectType>
    </Parent>
  </WebPageItemWebsiteChannelID>
</cms.webpageitem>