<?xml version="1.0" encoding="utf-8"?>
<media.file>
  <FileCreatedByUserID>
    <CodeName>administrator</CodeName>
    <GUID>6415b8ce-8072-4bcd-8e48-9d7178b826b7</GUID>
    <ObjectType>cms.user</ObjectType>
  </FileCreatedByUserID>
  <FileCreatedWhen>2024-02-02 04:52:33Z</FileCreatedWhen>
  <FileDescription />
  <FileExtension>.svg</FileExtension>
  <FileGUID>2386634e-8d53-4921-b57f-d06bc3b6dd1f</FileGUID>
  <FileLibraryID>
    <CodeName>Media</CodeName>
    <GUID>34e8ba8d-573a-4376-961f-c5290f5f71a9</GUID>
    <ObjectType>media.library</ObjectType>
  </FileLibraryID>
  <FileMimeType>image/svg+xml</FileMimeType>
  <FileModifiedByUserID>
    <CodeName>administrator</CodeName>
    <GUID>6415b8ce-8072-4bcd-8e48-9d7178b826b7</GUID>
    <ObjectType>cms.user</ObjectType>
  </FileModifiedByUserID>
  <FileName>Photosnap-logo</FileName>
  <FilePath>Photosnap-logo.svg</FilePath>
  <FileSize>7000</FileSize>
  <FileTitle />
</media.file>